pan_threat_vault_python-0.4.0.data/scripts/tvapi.py
pan_threat_vault_python-0.4.0.dist-info/licenses/LICENSE.txt
pantv/__init__.py
pantv/mixin.py
pantv/v1aioapi.py
pantv/v1api.py
pan_threat_vault_python-0.4.0.dist-info/METADATA
pan_threat_vault_python-0.4.0.dist-info/WHEEL
pan_threat_vault_python-0.4.0.dist-info/top_level.txt
pan_threat_vault_python-0.4.0.dist-info/RECORD
