Metadata-Version: 2.4
Name: pan-threat-vault-python
Version: 0.4.0
Summary: Python interface to the Palo Alto Networks Threat Vault API
Home-page: https://github.com/PaloAltoNetworks/pan-threat-vault-python
Author: Palo Alto Networks, Inc.
Author-email: devrel@paloaltonetworks.com
License: ISC
Classifier: Programming Language :: Python :: 3
Classifier: License :: OSI Approved :: ISC License (ISCL)
Requires-Python: >=3.9
License-File: LICENSE.txt
Requires-Dist: aiohttp>=3.11.18
Requires-Dist: requests>=2.32.3
Dynamic: license-file
